Workbook
Name CECO_CODIGOS: 'CATALOGO CECO'!$A$2:$A$550

Sheet INSTRUCCIONES
A1: PLANTILLA DE CARGA DIRECTA – COSTOS POR CENTRO DE COSTOS (CECO)
A2: ESE Departamental de Primer Nivel Moreno y Clavijo
A4: 1. Diligencie la hoja CARGA desde la fila 2. Una fila por CECO y cuenta contable del mes.
A5: 2. Columnas azules (editables): PERIODO (AAAA-MM), CODIGO CECO (elíjalo de la lista), CUENTA, NOMBRE CUENTA, VALOR y DESCRIPCION.
A6: 3. Las columnas grises (AUTO) se calculan solas: nombre del CECO, código de resolución, llave CECO|SEDE, estado y validación. No las edite.
A7: 4. Revise la columna VALIDACIÓN: solo las filas en OK se cargarán. Los mensajes indican qué corregir.
A8: 5. Estados: ACTIVO = se carga · VERIFICAR = validar con contabilidad/habilitación (no se carga) · NO APLICA = servicio no habilitado en primer nivel (no debería tener gasto) · EXCLUIR = partida que no es costo.
A9: 6. Revise la hoja RESUMEN antes de cargar: total por estado y número de filas con error.
A10: 7. Guarde el archivo (.xlsx) y procéselo: python -m homologacion_ceco procesar PLANTILLA.xlsx --salida resultado.xlsx
A11: Puede incluirlo en un ZIP con otros archivos; la herramienta reconoce esta plantilla sin configuración adicional.
A12: 8. Montos: escriba números (sin texto). Si pega desde otro sistema, use Pegado especial > Valores.
A13: 9. Si un CECO no aparece en la lista, no lo invente: solicite su homologación (se agrega al archivo de referencia).
... A17: • Estado del CECO: solo ACTIVO se carga; los demás se reportan como retenidos en el resultado.

Sheet CARGA
A1: PERIODO | B1: CODIGO CECO | C1: CUENTA | D1: NOMBRE CUENTA | E1: VALOR | F1: DESCRIPCION | G1: NOMBRE CECO (AUTO) | H1: CECO RESOLUCIÓN (AUTO) | I1: LLAVE CECO|SEDE (AUTO) | J1: ESTADO (AUTO) | K1: VALIDACIÓN (AUTO)
G2: =IF(B2="","",IFERROR(VLOOKUP(--B2,'CATALOGO CECO'!$A$2:$H$550,2,FALSE),"CECO NO EXISTE")) | H2: =IF(B2="","",IFERROR(VLOOKUP(--B2,'CATALOGO CECO'!$A$2:$H$550,3,FALSE),"")) | I2: =IF(B2="","",IFERROR(VLOOKUP(--B2,'CATALOGO CECO'!$A$2:$H$550,5,FALSE),"")) | J2: =IF(B2="","",IFERROR(VLOOKUP(--B2,'CATALOGO CECO'!$A$2:$H$550,8,FALSE),"")) | K2: =IF(COUNTA(A2:F2)=0,"",IF(OR(LEN(A2)<>7,MID(A2,5,1)<>"-",ISERROR(--LEFT(A2,4)),ISERROR(--RIGHT(A2,2))),"ERROR: PERIODO debe ser AAAA-MM",IF(B2="","ERROR: falta CODIGO CECO",IF(G2="CECO NO EXISTE","ERROR: CECO no existe en el catálogo",IF(C2="","ERROR: falta CUENTA",IF(ISERROR(--C2),"ERROR: CUENTA debe tener solo dígitos",IF(ISERROR(FIND(LEFT(C2,1),"567")),"ERROR: CUENTA fuera de las clases de costo",IF(NOT(ISNUMBER(E2)),"ERROR: VALOR debe ser numérico",IF(E2=0,"AVISO: valor cero (no se carga)",IF(J2<>"ACTIVO","NO SE CARGA: CECO en estado "&J2,"OK"))))))))))
G3: =IF(B3="","",IFERROR(VLOOKUP(--B3,'CATALOGO CECO'!$A$2:$H$550,2,FALSE),"CECO NO EXISTE")) | H3: =IF(B3="","",IFERROR(VLOOKUP(--B3,'CATALOGO CECO'!$A$2:$H$550,3,FALSE),"")) | I3: =IF(B3="","",IFERROR(VLOOKUP(--B3,'CATALOGO CECO'!$A$2:$H$550,5,FALSE),"")) | J3: =IF(B3="","",IFERROR(VLOOKUP(--B3,'CATALOGO CECO'!$A$2:$H$550,8,FALSE),"")) | K3: =IF(COUNTA(A3:F3)=0,"",IF(OR(LEN(A3)<>7,MID(A3,5,1)<>"-",ISERROR(--LEFT(A3,4)),ISERROR(--RIGHT(A3,2))),"ERROR: PERIODO debe ser AAAA-MM",IF(B3="","ERROR: falta CODIGO CECO",IF(G3="CECO NO EXISTE","ERROR: CECO no existe en el catálogo",IF(C3="","ERROR: falta CUENTA",IF(ISERROR(--C3),"ERROR: CUENTA debe tener solo dígitos",IF(ISERROR(FIND(LEFT(C3,1),"567")),"ERROR: CUENTA fuera de las clases de costo",IF(NOT(ISNUMBER(E3)),"ERROR: VALOR debe ser numérico",IF(E3=0,"AVISO: valor cero (no se carga)",IF(J3<>"ACTIVO","NO SE CARGA: CECO en estado "&J3,"OK"))))))))))
G4: =IF(B4="","",IFERROR(VLOOKUP(--B4,'CATALOGO CECO'!$A$2:$H$550,2,FALSE),"CECO NO EXISTE")) | H4: =IF(B4="","",IFERROR(VLOOKUP(--B4,'CATALOGO CECO'!$A$2:$H$550,3,FALSE),"")) | I4: =IF(B4="","",IFERROR(VLOOKUP(--B4,'CATALOGO CECO'!$A$2:$H$550,5,FALSE),"")) | J4: =IF(B4="","",IFERROR(VLOOKUP(--B4,'CATALOGO CECO'!$A$2:$H$550,8,FALSE),"")) | K4: =IF(COUNTA(A4:F4)=0,"",IF(OR(LEN(A4)<>7,MID(A4,5,1)<>"-",ISERROR(--LEFT(A4,4)),ISERROR(--RIGHT(A4,2))),"ERROR: PERIODO debe ser AAAA-MM",IF(B4="","ERROR: falta CODIGO CECO",IF(G4="CECO NO EXISTE","ERROR: CECO no existe en el catálogo",IF(C4="","ERROR: falta CUENTA",IF(ISERROR(--C4),"ERROR: CUENTA debe tener solo dígitos",IF(ISERROR(FIND(LEFT(C4,1),"567")),"ERROR: CUENTA fuera de las clases de costo",IF(NOT(ISNUMBER(E4)),"ERROR: VALOR debe ser numérico",IF(E4=0,"AVISO: valor cero (no se carga)",IF(J4<>"ACTIVO","NO SE CARGA: CECO en estado "&J4,"OK"))))))))))
G5: =IF(B5="","",IFERROR(VLOOKUP(--B5,'CATALOGO CECO'!$A$2:$H$550,2,FALSE),"CECO NO EXISTE")) | H5: =IF(B5="","",IFERROR(VLOOKUP(--B5,'CATALOGO CECO'!$A$2:$H$550,3,FALSE),"")) | I5: =IF(B5="","",IFERROR(VLOOKUP(--B5,'CATALOGO CECO'!$A$2:$H$550,5,FALSE),"")) | J5: =IF(B5="","",IFERROR(VLOOKUP(--B5,'CATALOGO CECO'!$A$2:$H$550,8,FALSE),"")) | K5: =IF(COUNTA(A5:F5)=0,"",IF(OR(LEN(A5)<>7,MID(A5,5,1)<>"-",ISERROR(--LEFT(A5,4)),ISERROR(--RIGHT(A5,2))),"ERROR: PERIODO debe ser AAAA-MM",IF(B5="","ERROR: falta CODIGO CECO",IF(G5="CECO NO EXISTE","ERROR: CECO no existe en el catálogo",IF(C5="","ERROR: falta CUENTA",IF(ISERROR(--C5),"ERROR: CUENTA debe tener solo dígitos",IF(ISERROR(FIND(LEFT(C5,1),"567")),"ERROR: CUENTA fuera de las clases de costo",IF(NOT(ISNUMBER(E5)),"ERROR: VALOR debe ser numérico",IF(E5=0,"AVISO: valor cero (no se carga)",IF(J5<>"ACTIVO","NO SE CARGA: CECO en estado "&J5,"OK"))))))))))
G6: =IF(B6="","",IFERROR(VLOOKUP(--B6,'CATALOGO CECO'!$A$2:$H$550,2,FALSE),"CECO NO EXISTE")) | H6: =IF(B6="","",IFERROR(VLOOKUP(--B6,'CATALOGO CECO'!$A$2:$H$550,3,FALSE),"")) | I6: =IF(B6="","",IFERROR(VLOOKUP(--B6,'CATALOGO CECO'!$A$2:$H$550,5,FALSE),"")) | J6: =IF(B6="","",IFERROR(VLOOKUP(--B6,'CATALOGO CECO'!$A$2:$H$550,8,FALSE),"")) | K6: =IF(COUNTA(A6:F6)=0,"",IF(OR(LEN(A6)<>7,MID(A6,5,1)<>"-",ISERROR(--LEFT(A6,4)),ISERROR(--RIGHT(A6,2))),"ERROR: PERIODO debe ser AAAA-MM",IF(B6="","ERROR: falta CODIGO CECO",IF(G6="CECO NO EXISTE","ERROR: CECO no existe en el catálogo",IF(C6="","ERROR: falta CUENTA",IF(ISERROR(--C6),"ERROR: CUENTA debe tener solo dígitos",IF(ISERROR(FIND(LEFT(C6,1),"567")),"ERROR: CUENTA fuera de las clases de costo",IF(NOT(ISNUMBER(E6)),"ERROR: VALOR debe ser numérico",IF(E6=0,"AVISO: valor cero (no se carga)",IF(J6<>"ACTIVO","NO SE CARGA: CECO en estado "&J6,"OK"))))))))))
G7: =IF(B7="","",IFERROR(VLOOKUP(--B7,'CATALOGO CECO'!$A$2:$H$550,2,FALSE),"CECO NO EXISTE")) | H7: =IF(B7="","",IFERROR(VLOOKUP(--B7,'CATALOGO CECO'!$A$2:$H$550,3,FALSE),"")) | I7: =IF(B7="","",IFERROR(VLOOKUP(--B7,'CATALOGO CECO'!$A$2:$H$550,5,FALSE),"")) | J7: =IF(B7="","",IFERROR(VLOOKUP(--B7,'CATALOGO CECO'!$A$2:$H$550,8,FALSE),"")) | K7: =IF(COUNTA(A7:F7)=0,"",IF(OR(LEN(A7)<>7,MID(A7,5,1)<>"-",ISERROR(--LEFT(A7,4)),ISERROR(--RIGHT(A7,2))),"ERROR: PERIODO debe ser AAAA-MM",IF(B7="","ERROR: falta CODIGO CECO",IF(G7="CECO NO EXISTE","ERROR: CECO no existe en el catálogo",IF(C7="","ERROR: falta CUENTA",IF(ISERROR(--C7),"ERROR: CUENTA debe tener solo dígitos",IF(ISERROR(FIND(LEFT(C7,1),"567")),"ERROR: CUENTA fuera de las clases de costo",IF(NOT(ISNUMBER(E7)),"ERROR: VALOR debe ser numérico",IF(E7=0,"AVISO: valor cero (no se carga)",IF(J7<>"ACTIVO","NO SE CARGA: CECO en estado "&J7,"OK"))))))))))
G8: =IF(B8="","",IFERROR(VLOOKUP(--B8,'CATALOGO CECO'!$A$2:$H$550,2,FALSE),"CECO NO EXISTE")) | H8: =IF(B8="","",IFERROR(VLOOKUP(--B8,'CATALOGO CECO'!$A$2:$H$550,3,FALSE),"")) | I8: =IF(B8="","",IFERROR(VLOOKUP(--B8,'CATALOGO CECO'!$A$2:$H$550,5,FALSE),"")) | J8: =IF(B8="","",IFERROR(VLOOKUP(--B8,'CATALOGO CECO'!$A$2:$H$550,8,FALSE),"")) | K8: =IF(COUNTA(A8:F8)=0,"",IF(OR(LEN(A8)<>7,MID(A8,5,1)<>"-",ISERROR(--LEFT(A8,4)),ISERROR(--RIGHT(A8,2))),"ERROR: PERIODO debe ser AAAA-MM",IF(B8="","ERROR: falta CODIGO CECO",IF(G8="CECO NO EXISTE","ERROR: CECO no existe en el catálogo",IF(C8="","ERROR: falta CUENTA",IF(ISERROR(--C8),"ERROR: CUENTA debe tener solo dígitos",IF(ISERROR(FIND(LEFT(C8,1),"567")),"ERROR: CUENTA fuera de las clases de costo",IF(NOT(ISNUMBER(E8)),"ERROR: VALOR debe ser numérico",IF(E8=0,"AVISO: valor cero (no se carga)",IF(J8<>"ACTIVO","NO SE CARGA: CECO en estado "&J8,"OK"))))))))))
G9: =IF(B9="","",IFERROR(VLOOKUP(--B9,'CATALOGO CECO'!$A$2:$H$550,2,FALSE),"CECO NO EXISTE")) | H9: =IF(B9="","",IFERROR(VLOOKUP(--B9,'CATALOGO CECO'!$A$2:$H$550,3,FALSE),"")) | I9: =IF(B9="","",IFERROR(VLOOKUP(--B9,'CATALOGO CECO'!$A$2:$H$550,5,FALSE),"")) | J9: =IF(B9="","",IFERROR(VLOOKUP(--B9,'CATALOGO CECO'!$A$2:$H$550,8,FALSE),"")) | K9: =IF(COUNTA(A9:F9)=0,"",IF(OR(LEN(A9)<>7,MID(A9,5,1)<>"-",ISERROR(--LEFT(A9,4)),ISERROR(--RIGHT(A9,2))),"ERROR: PERIODO debe ser AAAA-MM",IF(B9="","ERROR: falta CODIGO CECO",IF(G9="CECO NO EXISTE","ERROR: CECO no existe en el catálogo",IF(C9="","ERROR: falta CUENTA",IF(ISERROR(--C9),"ERROR: CUENTA debe tener solo dígitos",IF(ISERROR(FIND(LEFT(C9,1),"567")),"ERROR: CUENTA fuera de las clases de costo",IF(NOT(ISNUMBER(E9)),"ERROR: VALOR debe ser numérico",IF(E9=0,"AVISO: valor cero (no se carga)",IF(J9<>"ACTIVO","NO SE CARGA: CECO en estado "&J9,"OK"))))))))))
G10: =IF(B10="","",IFERROR(VLOOKUP(--B10,'CATALOGO CECO'!$A$2:$H$550,2,FALSE),"CECO NO EXISTE")) | H10: =IF(B10="","",IFERROR(VLOOKUP(--B10,'CATALOGO CECO'!$A$2:$H$550,3,FALSE),"")) | I10: =IF(B10="","",IFERROR(VLOOKUP(--B10,'CATALOGO CECO'!$A$2:$H$550,5,FALSE),"")) | J10: =IF(B10="","",IFERROR(VLOOKUP(--B10,'CATALOGO CECO'!$A$2:$H$550,8,FALSE),"")) | K10: =IF(COUNTA(A10:F10)=0,"",IF(OR(LEN(A10)<>7,MID(A10,5,1)<>"-",ISERROR(--LEFT(A10,4)),ISERROR(--RIGHT(A10,2))),"ERROR: PERIODO debe ser AAAA-MM",IF(B10="","ERROR: falta CODIGO CECO",IF(G10="CECO NO EXISTE","ERROR: CECO no existe en el catálogo",IF(C10="","ERROR: falta CUENTA",IF(ISERROR(--C10),"ERROR: CUENTA debe tener solo dígitos",IF(ISERROR(FIND(LEFT(C10,1),"567")),"ERROR: CUENTA fuera de las clases de costo",IF(NOT(ISNUMBER(E10)),"ERROR: VALOR debe ser numérico",IF(E10=0,"AVISO: valor cero (no se carga)",IF(J10<>"ACTIVO","NO SE CARGA: CECO en estado "&J10,"OK"))))))))))
G11: =IF(B11="","",IFERROR(VLOOKUP(--B11,'CATALOGO CECO'!$A$2:$H$550,2,FALSE),"CECO NO EXISTE")) | H11: =IF(B11="","",IFERROR(VLOOKUP(--B11,'CATALOGO CECO'!$A$2:$H$550,3,FALSE),"")) | I11: =IF(B11="","",IFERROR(VLOOKUP(--B11,'CATALOGO CECO'!$A$2:$H$550,5,FALSE),"")) | J11: =IF(B11="","",IFERROR(VLOOKUP(--B11,'CATALOGO CECO'!$A$2:$H$550,8,FALSE),"")) | K11: =IF(COUNTA(A11:F11)=0,"",IF(OR(LEN(A11)<>7,MID(A11,5,1)<>"-",ISERROR(--LEFT(A11,4)),ISERROR(--RIGHT(A11,2))),"ERROR: PERIODO debe ser AAAA-MM",IF(B11="","ERROR: falta CODIGO CECO",IF(G11="CECO NO EXISTE","ERROR: CECO no existe en el catálogo",IF(C11="","ERROR: falta CUENTA",IF(ISERROR(--C11),"ERROR: CUENTA debe tener solo dígitos",IF(ISERROR(FIND(LEFT(C11,1),"567")),"ERROR: CUENTA fuera de las clases de costo",IF(NOT(ISNUMBER(E11)),"ERROR: VALOR debe ser numérico",IF(E11=0,"AVISO: valor cero (no se carga)",IF(J11<>"ACTIVO","NO SE CARGA: CECO en estado "&J11,"OK"))))))))))
G12: =IF(B12="","",IFERROR(VLOOKUP(--B12,'CATALOGO CECO'!$A$2:$H$550,2,FALSE),"CECO NO EXISTE")) | H12: =IF(B12="","",IFERROR(VLOOKUP(--B12,'CATALOGO CECO'!$A$2:$H$550,3,FALSE),"")) | I12: =IF(B12="","",IFERROR(VLOOKUP(--B12,'CATALOGO CECO'!$A$2:$H$550,5,FALSE),"")) | J12: =IF(B12="","",IFERROR(VLOOKUP(--B12,'CATALOGO CECO'!$A$2:$H$550,8,FALSE),"")) | K12: =IF(COUNTA(A12:F12)=0,"",IF(OR(LEN(A12)<>7,MID(A12,5,1)<>"-",ISERROR(--LEFT(A12,4)),ISERROR(--RIGHT(A12,2))),"ERROR: PERIODO debe ser AAAA-MM",IF(B12="","ERROR: falta CODIGO CECO",IF(G12="CECO NO EXISTE","ERROR: CECO no existe en el catálogo",IF(C12="","ERROR: falta CUENTA",IF(ISERROR(--C12),"ERROR: CUENTA debe tener solo dígitos",IF(ISERROR(FIND(LEFT(C12,1),"567")),"ERROR: CUENTA fuera de las clases de costo",IF(NOT(ISNUMBER(E12)),"ERROR: VALOR debe ser numérico",IF(E12=0,"AVISO: valor cero (no se carga)",IF(J12<>"ACTIVO","NO SE CARGA: CECO en estado "&J12,"OK"))))))))))
G13: =IF(B13="","",IFERROR(VLOOKUP(--B13,'CATALOGO CECO'!$A$2:$H$550,2,FALSE),"CECO NO EXISTE")) | H13: =IF(B13="","",IFERROR(VLOOKUP(--B13,'CATALOGO CECO'!$A$2:$H$550,3,FALSE),"")) | I13: =IF(B13="","",IFERROR(VLOOKUP(--B13,'CATALOGO CECO'!$A$2:$H$550,5,FALSE),"")) | J13: =IF(B13="","",IFERROR(VLOOKUP(--B13,'CATALOGO CECO'!$A$2:$H$550,8,FALSE),"")) | K13: =IF(COUNTA(A13:F13)=0,"",IF(OR(LEN(A13)<>7,MID(A13,5,1)<>"-",ISERROR(--LEFT(A13,4)),ISERROR(--RIGHT(A13,2))),"ERROR: PERIODO debe ser AAAA-MM",IF(B13="","ERROR: falta CODIGO CECO",IF(G13="CECO NO EXISTE","ERROR: CECO no existe en el catálogo",IF(C13="","ERROR: falta CUENTA",IF(ISERROR(--C13),"ERROR: CUENTA debe tener solo dígitos",IF(ISERROR(FIND(LEFT(C13,1),"567")),"ERROR: CUENTA fuera de las clases de costo",IF(NOT(ISNUMBER(E13)),"ERROR: VALOR debe ser numérico",IF(E13=0,"AVISO: valor cero (no se carga)",IF(J13<>"ACTIVO","NO SE CARGA: CECO en estado "&J13,"OK"))))))))))
... G3001: =IF(B3001="","",IFERROR(VLOOKUP(--B3001,'CATALOGO CECO'!$A$2:$H$550,2,FALSE),"CECO NO EXISTE")) | H3001: =IF(B3001="","",IFERROR(VLOOKUP(--B3001,'CATALOGO CECO'!$A$2:$H$550,3,FALSE),"")) | I3001: =IF(B3001="","",IFERROR(VLOOKUP(--B3001,'CATALOGO CECO'!$A$2:$H$550,5,FALSE),"")) | J3001: =IF(B3001="","",IFERROR(VLOOKUP(--B3001,'CATALOGO CECO'!$A$2:$H$550,8,FALSE),"")) | K3001: =IF(COUNTA(A3001:F3001)=0,"",IF(OR(LEN(A3001)<>7,MID(A3001,5,1)<>"-",ISERROR(--LEFT(A3001,4)),ISERROR(--RIGHT(A3001,2))),"ERROR: PERIODO debe ser AAAA-MM",IF(B3001="","ERROR: falta CODIGO CECO",IF(G3001="CECO NO EXISTE","ERROR: CECO no existe en el catálogo",IF(C3001="","ERROR: falta CUENTA",IF(ISERROR(--C3001),"ERROR: CUENTA debe tener solo dígitos",IF(ISERROR(FIND(LEFT(C3001,1),"567")),"ERROR: CUENTA fuera de las clases de costo",IF(NOT(ISNUMBER(E3001)),"ERROR: VALOR debe ser numérico",IF(E3001=0,"AVISO: valor cero (no se carga)",IF(J3001<>"ACTIVO","NO SE CARGA: CECO en estado "&J3001,"OK"))))))))))

Sheet CATALOGO CECO
A1: CODIGO CECO | B1: NOMBRE CECO | C1: CECO RESOLUCION | D1: NOMBRE CECO RESOLUCION | E1: LLAVE CECO|SEDE | F1: SEDE / IPS | G1: TIPO CECO | H1: ESTADO
A2: 1010204 | B2: ESE01-TAME-PROMOCION Y MANTENIMIENTO | C2: N03 | D2: PROMOCIÓN Y PREVENCIÓN | E2: N03|ESE01 | F2: ESE01 - Sede Administrativa (Tame) | G2: PRODUCTIVO (final) | H2: ACTIVO
A3: 1010205 | B3: ESE01- SEDE ADMINISTRATIVA - OTRAS ACTIVIDADES EXTRAMURALES | C3: K25 | D3: SALUD PUBLICA | E3: K25|ESE01 | F3: ESE01 - Sede Administrativa (Tame) | G3: PRODUCTIVO (final) | H3: ACTIVO
A4: 1010220 | B4: ESE-MANTENIMIENTO PREVENTIVO Y CORRECTIVO | C4: R03 | D4: MANTENIMIENTO | E4: R03|ESE01 | F4: ESE01 - Sede Administrativa (Tame) | G4: ADMINISTRATIVO | H4: ACTIVO
A5: 1010606 | B5: ESE01-TAME-FARMACIA E INSUMOS HOPITALARIOS | C5: M05 | D5: FARMACIA | E5: M05|ESE01 | F5: ESE01 - Sede Administrativa (Tame) | G5: APOYO ASISTENCIAL (intermedio) | H5: ACTIVO
A6: 1010706 | B6: ESE- INGENIERIA CIVIL | C6: R03 | D6: MANTENIMIENTO | E6: R03|ESE01 | F6: ESE01 - Sede Administrativa (Tame) | G6: ADMINISTRATIVO | H6: ACTIVO
A7: 1020101 | B7: HSLA-ARAUQUITA-CONSULTA Y PROCEDIMIENTOS | C7: B01 | D7: CONSULTA URGENCIAS | E7: B01|HSLA | F7: HSLA - Arauquita | G7: PRODUCTIVO (final) | H7: ACTIVO
A8: 1020102 | B8: HSLA-ARAUQUITA-OBSERVACIONES | C8: B02 | D8: OBSERVACIÓN | E8: B02|HSLA | F8: HSLA - Arauquita | G8: PRODUCTIVO (final) | H8: ACTIVO
A9: 1020201 | B9: HSLA-ARAUQUITA-CONSULTA EXTERNA | C9: A10 | D9: MEDICINA GENERAL | E9: A10|HSLA | F9: HSLA - Arauquita | G9: PRODUCTIVO (final) | H9: ACTIVO
A10: 1020202 | B10: HSLA-ARAUQUITA-CONSULTA ESPECIALIZADA | C10: A32 | D10: OTRAS CONSULTAS Y PROCEDIMIENTOS | E10: A32|HSLA | F10: HSLA - Arauquita | G10: PRODUCTIVO (final) | H10: ACTIVO
A11: 1020203 | B11: HSLA-ARAUQUITA-SALUD ORAL | C11: E01 | D11: ODONTOLOGÍA GENERAL | E11: E01|HSLA | F11: HSLA - Arauquita | G11: PRODUCTIVO (final) | H11: ACTIVO
A12: 1020204 | B12: HSLA-ARAUQUITA-PROMOCION Y MANTENIMIENTO | C12: N03 | D12: PROMOCIÓN Y PREVENCIÓN | E12: N03|HSLA | F12: HSLA - Arauquita | G12: PRODUCTIVO (final) | H12: ACTIVO
A13: 1020205 | B13: HSLA-ARAUQUITA-OTRAS ACTIVIDADES EXTRAMURALES | C13: K25 | D13: SALUD PUBLICA | E13: K25|HSLA | F13: HSLA - Arauquita | G13: PRODUCTIVO (final) | H13: ACTIVO
... A550: 7090101 | B550: ESE01-CONSULTORIA-PROFESIONAL | C550: R01 | D550: COORDINACIÓN ADMINISTRATIVA | E550: R01|ESE01 | F550: ESE01 - Sede Administrativa (Tame) | G550: ADMINISTRATIVO | H550: VERIFICAR

Sheet RESUMEN
A1: RESUMEN DE VALIDACIÓN ANTES DE CARGAR
A3: CONCEPTO | B3: FILAS | C3: VALOR
A4: Filas diligenciadas | B4: =COUNTIF(CARGA!K2:K3001,"?*") | C4: =SUM(CARGA!E2:E3001)
A5: Filas listas para cargar (OK) | B5: =COUNTIF(CARGA!K2:K3001,"OK") | C5: =SUMIFS(CARGA!E2:E3001,CARGA!K2:K3001,"OK")
A6: Filas con ERROR (corregir) | B6: =COUNTIF(CARGA!K2:K3001,"ERROR*") | C6: =SUMIFS(CARGA!E2:E3001,CARGA!K2:K3001,"ERROR*")
A7: Filas que no se cargarán por estado del CECO | B7: =COUNTIF(CARGA!K2:K3001,"NO SE CARGA*") | C7: =SUMIFS(CARGA!E2:E3001,CARGA!K2:K3001,"NO SE CARGA*")
A8: Filas con valor cero | B8: =COUNTIF(CARGA!K2:K3001,"AVISO*")
A10: ESTADO DEL CECO | B10: FILAS | C10: VALOR
A11: ACTIVO | B11: =COUNTIF(CARGA!J2:J3001,A11) | C11: =SUMIFS(CARGA!E2:E3001,CARGA!J2:J3001,A11)
A12: VERIFICAR | B12: =COUNTIF(CARGA!J2:J3001,A12) | C12: =SUMIFS(CARGA!E2:E3001,CARGA!J2:J3001,A12)
A13: NO APLICA | B13: =COUNTIF(CARGA!J2:J3001,A13) | C13: =SUMIFS(CARGA!E2:E3001,CARGA!J2:J3001,A13)
A14: EXCLUIR | B14: =COUNTIF(CARGA!J2:J3001,A14) | C14: =SUMIFS(CARGA!E2:E3001,CARGA!J2:J3001,A14)
