Workbook

Sheet RESUMEN HOMOLOGACIÓN
B2: HOMOLOGACIÓN DE CENTROS DE COSTOS – ESTADO FINANCIERO vs. RESOLUCIÓN
B3: ESE Departamental de Primer Nivel Moreno y Clavijo · Base para la herramienta de costos
B5: Estado para costeo | C5: N° CECO | D5: %
B6: ACTIVO | C6: =COUNTIF('C COSTOS ESTADO FINANCIERO'!$J:$J,B6) -> 399 | D6: =IFERROR(C6/$C$10,0) -> 0.72677596
B7: VERIFICAR | C7: =COUNTIF('C COSTOS ESTADO FINANCIERO'!$J:$J,B7) -> 51 | D7: =IFERROR(C7/$C$10,0) -> 0.092896175
B8: NO APLICA | C8: =COUNTIF('C COSTOS ESTADO FINANCIERO'!$J:$J,B8) -> 96 | D8: =IFERROR(C8/$C$10,0) -> 0.17486339
B9: EXCLUIR | C9: =COUNTIF('C COSTOS ESTADO FINANCIERO'!$J:$J,B9) -> 3 | D9: =IFERROR(C9/$C$10,0) -> 0.0054644809
B10: TOTAL CECO E.F. | C10: =SUM(C6:C9) -> 549 | D10: =SUM(D6:D9) -> 1
B12: Control de calidad
B13: CECO E.F. en catálogo origen | C13: =COUNTA('C COSTOS ESTADO FINANCIERO'!$A:$A)-1 -> 549
B14: CECO con código homologado | C14: =COUNTA('C COSTOS ESTADO FINANCIERO'!$D:$D)-1 -> 549
B15: Códigos homologados no válidos en resolución | C15: =COUNTIF('C COSTOS ESTADO FINANCIERO'!$E:$E,"CÓDIGO NO VÁLIDO") -> 0
B16: ACTIVOS asignados a CECO fuera de "Utilizados" | C16: =COUNTIFS('C COSTOS ESTADO FINANCIERO'!$J:$J,"ACTIVO",'C COSTOS ESTADO FINANCIERO'!$F:$F,"NO") -> 43
B17: CECO de resolución "Utilizados" sin ningún CECO E.F. asignado | C17: =COUNTIF('CENTROS DE COSTOS UTILIZADOS'!$D:$D,0) -> 10
B19: Por tipo de CECO (solo ACTIVOS)
B20: PRODUCTIVO (final) | C20: =COUNTIFS('C COSTOS ESTADO FINANCIERO'!$H:$H,B20,'C COSTOS ESTADO FINANCIERO'!$J:$J,"ACTIVO") -> 123
B21: APOYO ASISTENCIAL (intermedio) | C21: =COUNTIFS('C COSTOS ESTADO FINANCIERO'!$H:$H,B21,'C COSTOS ESTADO FINANCIERO'!$J:$J,"ACTIVO") -> 46
B22: APOYO LOGÍSTICO | C22: =COUNTIFS('C COSTOS ESTADO FINANCIERO'!$H:$H,B22,'C COSTOS ESTADO FINANCIERO'!$J:$J,"ACTIVO") -> 95
B23: ADMINISTRATIVO | C23: =COUNTIFS('C COSTOS ESTADO FINANCIERO'!$H:$H,B23,'C COSTOS ESTADO FINANCIERO'!$J:$J,"ACTIVO") -> 135
B25: Cómo usar
B26: 1. Hoja "C COSTOS ESTADO FINANCIERO", columna D (azul) = código de la resolución asignado. Es editable con lista desplegable; el resto de columnas se recalcula.
B27: 2. Columna G = llave CECO|SEDE para cargar en la herramienta de costos (permite costear el mismo servicio por IPS).
B28: 3. ESTADO: ACTIVO = cargar a la herramienta · VERIFICAR (amarillo) = validar con contabilidad/habilitación · NO APLICA (gris) = estructura CHIP no habilitada en primer nivel · EXCLUIR (rojo) = partidas que no son costo.
B29: 4. Los ACTIVOS que caen en un CECO que no está en "Utilizados" (I01, D02, P01, P03, A32, L04, M07, etc.) deben agregarse a esa lista para que la herramienta los reconozca.
B30: 5. Homologación realizada por la estructura del código (últimos 4 dígitos = servicio CHIP) y por nombre para los CECO de sede central e irregulares.

Sheet C COSTOS ESTADO FINANCIERO
A1: Codigo | B1: Nombre | C1: Activo | D1: CENTRO DE COSTOS RESOLUCION HOMOLOGADO | E1: NOMBRE CECO RESOLUCIÓN | F1: ¿EN LISTA UTILIZADOS? | G1: LLAVE HERRAMIENTA (CECO|SEDE) | H1: TIPO CECO | I1: SEDE / IPS | J1: ESTADO PARA COSTEO | K1: CONFIANZA | L1: CRITERIO DE HOMOLOGACIÓN | M1: MÉTODO
A2: 1020101 | B2: HSLA-ARAUQUITA-CONSULTA Y PROCEDIMIENTOS | D2: B01 | E2: =IFERROR(INDEX('CENTROS DE COSTOS RESOLUCION'!$C:$C,MATCH(D2,'CENTROS DE COSTOS RESOLUCION'!$B:$B,0)),"CÓDIGO NO VÁLIDO") -> CONSULTA URGENCIAS | F2: =IF(COUNTIF('CENTROS DE COSTOS UTILIZADOS'!$B:$B,D2)>0,"SÍ","NO") -> SÍ | G2: =D2&"|"&LEFT(I2,FIND(" ",I2&" ")-1) -> B01|HSLA | H2: PRODUCTIVO (final) | I2: HSLA - Arauquita | J2: ACTIVO | K2: Alta | L2: Urgencias: consulta y procedimientos. Si se requiere detalle, distribuir B01/B03 según producción | M2: Estructura de código (servicio)
A3: 1020102 | B3: HSLA-ARAUQUITA-OBSERVACIONES | D3: B02 | E3: =IFERROR(INDEX('CENTROS DE COSTOS RESOLUCION'!$C:$C,MATCH(D3,'CENTROS DE COSTOS RESOLUCION'!$B:$B,0)),"CÓDIGO NO VÁLIDO") -> OBSERVACIÓN | F3: =IF(COUNTIF('CENTROS DE COSTOS UTILIZADOS'!$B:$B,D3)>0,"SÍ","NO") -> SÍ | G3: =D3&"|"&LEFT(I3,FIND(" ",I3&" ")-1) -> B02|HSLA | H3: PRODUCTIVO (final) | I3: HSLA - Arauquita | J3: ACTIVO | K3: Alta | L3: Observación de urgencias | M3: Estructura de código (servicio)
A4: 1020201 | B4: HSLA-ARAUQUITA-CONSULTA EXTERNA | D4: A10 | E4: =IFERROR(INDEX('CENTROS DE COSTOS RESOLUCION'!$C:$C,MATCH(D4,'CENTROS DE COSTOS RESOLUCION'!$B:$B,0)),"CÓDIGO NO VÁLIDO") -> MEDICINA GENERAL | F4: =IF(COUNTIF('CENTROS DE COSTOS UTILIZADOS'!$B:$B,D4)>0,"SÍ","NO") -> SÍ | G4: =D4&"|"&LEFT(I4,FIND(" ",I4&" ")-1) -> A10|HSLA | H4: PRODUCTIVO (final) | I4: HSLA - Arauquita | J4: ACTIVO | K4: Alta | L4: Consulta externa general = Medicina general | M4: Estructura de código (servicio)
A5: 1020202 | B5: HSLA-ARAUQUITA-CONSULTA ESPECIALIZADA | D5: A32 | E5: =IFERROR(INDEX('CENTROS DE COSTOS RESOLUCION'!$C:$C,MATCH(D5,'CENTROS DE COSTOS RESOLUCION'!$B:$B,0)),"CÓDIGO NO VÁLIDO") -> OTRAS CONSULTAS Y PROCEDIMIENTOS | F5: =IF(COUNTIF('CENTROS DE COSTOS UTILIZADOS'!$B:$B,D5)>0,"SÍ","NO") -> NO | G5: =D5&"|"&LEFT(I5,FIND(" ",I5&" ")-1) -> A32|HSLA | H5: PRODUCTIVO (final) | I5: HSLA - Arauquita | J5: ACTIVO | K5: Media | L5: Consulta especializada agrupada. Distribuir a A24/A26/A18/A28 según producción por especialidad | M5: Estructura de código (servicio)
A6: 1020203 | B6: HSLA-ARAUQUITA-SALUD ORAL | D6: E01 | E6: =IFERROR(INDEX('CENTROS DE COSTOS RESOLUCION'!$C:$C,MATCH(D6,'CENTROS DE COSTOS RESOLUCION'!$B:$B,0)),"CÓDIGO NO VÁLIDO") -> ODONTOLOGÍA GENERAL | F6: =IF(COUNTIF('CENTROS DE COSTOS UTILIZADOS'!$B:$B,D6)>0,"SÍ","NO") -> SÍ | G6: =D6&"|"&LEFT(I6,FIND(" ",I6&" ")-1) -> E01|HSLA | H6: PRODUCTIVO (final) | I6: HSLA - Arauquita | J6: ACTIVO | K6: Alta | L6: Salud oral = Odontología general | M6: Estructura de código (servicio)
A7: 1020204 | B7: HSLA-ARAUQUITA-PROMOCION Y MANTENIMIENTO | D7: N03 | E7: =IFERROR(INDEX('CENTROS DE COSTOS RESOLUCION'!$C:$C,MATCH(D7,'CENTROS DE COSTOS RESOLUCION'!$B:$B,0)),"CÓDIGO NO VÁLIDO") -> PROMOCIÓN Y PREVENCIÓN | F7: =IF(COUNTIF('CENTROS DE COSTOS UTILIZADOS'!$B:$B,D7)>0,"SÍ","NO") -> SÍ | G7: =D7&"|"&LEFT(I7,FIND(" ",I7&" ")-1) -> N03|HSLA | H7: PRODUCTIVO (final) | I7: HSLA - Arauquita | J7: ACTIVO | K7: Alta | L7: Promoción y mantenimiento (RIAS) = Promoción y prevención | M7: Estructura de código (servicio)
A8: 1020205 | B8: HSLA-ARAUQUITA-OTRAS ACTIVIDADES EXTRAMURALES | D8: K25 | E8: =IFERROR(INDEX('CENTROS DE COSTOS RESOLUCION'!$C:$C,MATCH(D8,'CENTROS DE COSTOS RESOLUCION'!$B:$B,0)),"CÓDIGO NO VÁLIDO") -> SALUD PUBLICA | F8: =IF(COUNTIF('CENTROS DE COSTOS UTILIZADOS'!$B:$B,D8)>0,"SÍ","NO") -> SÍ | G8: =D8&"|"&LEFT(I8,FIND(" ",I8&" ")-1) -> K25|HSLA | H8: PRODUCTIVO (final) | I8: HSLA - Arauquita | J8: ACTIVO | K8: Media | L8: Extramural / PIC. Si se requiere detalle, desagregar en K10/K15/K17 | M8: Estructura de código (servicio)
A9: 1020301 | B9: HSLA-ARAUQUITA-HOSPITALACION-ESTANCIA GENERAL | D9: I01 | E9: =IFERROR(INDEX('CENTROS DE COSTOS RESOLUCION'!$C:$C,MATCH(D9,'CENTROS DE COSTOS RESOLUCION'!$B:$B,0)),"CÓDIGO NO VÁLIDO") -> HOSPITALIZACIÓN GENERAL | F9: =IF(COUNTIF('CENTROS DE COSTOS UTILIZADOS'!$B:$B,D9)>0,"SÍ","NO") -> NO | G9: =D9&"|"&LEFT(I9,FIND(" ",I9&" ")-1) -> I01|HSLA | H9: PRODUCTIVO (final) | I9: HSLA - Arauquita | J9: ACTIVO | K9: Alta | L9: Hospitalización estancia general | M9: Estructura de código (servicio)
A10: 1020302 | B10: HSLA-ARAUQUITA-CUIDADOS INTENSIVOS | D10: J02 | E10: =IFERROR(INDEX('CENTROS DE COSTOS RESOLUCION'!$C:$C,MATCH(D10,'CENTROS DE COSTOS RESOLUCION'!$B:$B,0)),"CÓDIGO NO VÁLIDO") -> UCI ADULTOS | F10: =IF(COUNTIF('CENTROS DE COSTOS UTILIZADOS'!$B:$B,D10)>0,"SÍ","NO") -> NO | G10: =D10&"|"&LEFT(I10,FIND(" ",I10&" ")-1) -> J02|HSLA | H10: PRODUCTIVO (final) | I10: HSLA - Arauquita | J10: NO APLICA | K10: Alta | L10: NO APLICA - servicio no habilitado en baja complejidad (mantener inactivo; validar que no reciba gasto) | M10: Estructura de código (servicio)
A11: 1020303 | B11: HSLA-ARAUQUITA-CUIDADOS INTERMEDIOS | D11: J05 | E11: =IFERROR(INDEX('CENTROS DE COSTOS RESOLUCION'!$C:$C,MATCH(D11,'CENTROS DE COSTOS RESOLUCION'!$B:$B,0)),"CÓDIGO NO VÁLIDO") -> UCI INTERMEDIOS ADULTOS | F11: =IF(COUNTIF('CENTROS DE COSTOS UTILIZADOS'!$B:$B,D11)>0,"SÍ","NO") -> NO | G11: =D11&"|"&LEFT(I11,FIND(" ",I11&" ")-1) -> J05|HSLA | H11: PRODUCTIVO (final) | I11: HSLA - Arauquita | J11: NO APLICA | K11: Alta | L11: NO APLICA - servicio no habilitado en baja complejidad (mantener inactivo; validar que no reciba gasto) | M11: Estructura de código (servicio)
A12: 1020304 | B12: HSLA-ARAUQUITA-RECIEN NACIDOS | D12: J09 | E12: =IFERROR(INDEX('CENTROS DE COSTOS RESOLUCION'!$C:$C,MATCH(D12,'CENTROS DE COSTOS RESOLUCION'!$B:$B,0)),"CÓDIGO NO VÁLIDO") -> UNIDAD DE RECIÉN NACIDOS | F12: =IF(COUNTIF('CENTROS DE COSTOS UTILIZADOS'!$B:$B,D12)>0,"SÍ","NO") -> NO | G12: =D12&"|"&LEFT(I12,FIND(" ",I12&" ")-1) -> J09|HSLA | H12: PRODUCTIVO (final) | I12: HSLA - Arauquita | J12: VERIFICAR | K12: Media | L12: Recién nacidos: validar si existe unidad habilitada; si no, el gasto va a D02/I01 | M12: Estructura de código (servicio)
A13: 1020305 | B13: HSLA-ARAUQUITA-HOSPITALIZACI.N SALUD MENTAL | D13: J10 | E13: =IFERROR(INDEX('CENTROS DE COSTOS RESOLUCION'!$C:$C,MATCH(D13,'CENTROS DE COSTOS RESOLUCION'!$B:$B,0)),"CÓDIGO NO VÁLIDO") -> UNIDAD SALUD MENTAL Y DESINTOXICACIÓN (BAJA COMPLEJIDAD) | F13: =IF(COUNTIF('CENTROS DE COSTOS UTILIZADOS'!$B:$B,D13)>0,"SÍ","NO") -> NO | G13: =D13&"|"&LEFT(I13,FIND(" ",I13&" ")-1) -> J10|HSLA | H13: PRODUCTIVO (final) | I13: HSLA - Arauquita | J13: NO APLICA | K13: Alta | L13: NO APLICA - servicio no habilitado en baja complejidad (mantener inactivo; validar que no reciba gasto) | M13: Estructura de código (servicio)
... A550: 4142217 | B550: ESE01 - TAME - SISTEMA ELECTRICO | D550: R03 | E550: =IFERROR(INDEX('CENTROS DE COSTOS RESOLUCION'!$C:$C,MATCH(D550,'CENTROS DE COSTOS RESOLUCION'!$B:$B,0)),"CÓDIGO NO VÁLIDO") -> MANTENIMIENTO | F550: =IF(COUNTIF('CENTROS DE COSTOS UTILIZADOS'!$B:$B,D550)>0,"SÍ","NO") -> SÍ | G550: =D550&"|"&LEFT(I550,FIND(" ",I550&" ")-1) -> R03|ESE01 | H550: ADMINISTRATIVO | I550: ESE01 - Sede Administrativa (Tame) | J550: ACTIVO | K550: Media | L550: Sistema eléctrico sede central | M550: Regla específica

Sheet CENTROS DE COSTOS UTILIZADOS
B1: CENTROS DE COSTOS UTILIZADOS
B3: CÓDIGO CECO | C3: NOMBRE CENTROS DE COSTOS | D3: N° CECO E.F. ACTIVOS ASIGNADOS
B4: A10 | C4: MEDICINA GENERAL | D4: =COUNTIFS('C COSTOS ESTADO FINANCIERO'!$D:$D,B4,'C COSTOS ESTADO FINANCIERO'!$J:$J,"ACTIVO") -> 8
B5: A18 | C5: PSICOLOGÍA | D5: =COUNTIFS('C COSTOS ESTADO FINANCIERO'!$D:$D,B5,'C COSTOS ESTADO FINANCIERO'!$J:$J,"ACTIVO") -> 0
B6: A24 | C6: GINECOLOGÍA Y OBSTETRICIA | D6: =COUNTIFS('C COSTOS ESTADO FINANCIERO'!$D:$D,B6,'C COSTOS ESTADO FINANCIERO'!$J:$J,"ACTIVO") -> 0
B7: A26 | C7: PEDIATRÍA | D7: =COUNTIFS('C COSTOS ESTADO FINANCIERO'!$D:$D,B7,'C COSTOS ESTADO FINANCIERO'!$J:$J,"ACTIVO") -> 0
B8: A28 | C8: CONSULTA PREANESTÉSICA | D8: =COUNTIFS('C COSTOS ESTADO FINANCIERO'!$D:$D,B8,'C COSTOS ESTADO FINANCIERO'!$J:$J,"ACTIVO") -> 0
B9: B01 | C9: CONSULTA URGENCIAS | D9: =COUNTIFS('C COSTOS ESTADO FINANCIERO'!$D:$D,B9,'C COSTOS ESTADO FINANCIERO'!$J:$J,"ACTIVO") -> 8
B10: B02 | C10: OBSERVACIÓN | D10: =COUNTIFS('C COSTOS ESTADO FINANCIERO'!$D:$D,B10,'C COSTOS ESTADO FINANCIERO'!$J:$J,"ACTIVO") -> 8
B11: B03 | C11: PROCEDIMIENTOS URGENCIAS | D11: =COUNTIFS('C COSTOS ESTADO FINANCIERO'!$D:$D,B11,'C COSTOS ESTADO FINANCIERO'!$J:$J,"ACTIVO") -> 0
B12: E01 | C12: ODONTOLOGÍA GENERAL | D12: =COUNTIFS('C COSTOS ESTADO FINANCIERO'!$D:$D,B12,'C COSTOS ESTADO FINANCIERO'!$J:$J,"ACTIVO") -> 8
B13: J17 | C13: CENTROS Y PUESTOS DE SALUD | D13: =COUNTIFS('C COSTOS ESTADO FINANCIERO'!$D:$D,B13,'C COSTOS ESTADO FINANCIERO'!$J:$J,"ACTIVO") -> 8
B14: K10 | C14: GESTIÓN Y ADMINISTRACIÓN DEL PROGRAMA AMPLIADO DE INMUNIZACIONES | D14: =COUNTIFS('C COSTOS ESTADO FINANCIERO'!$D:$D,B14,'C COSTOS ESTADO FINANCIERO'!$J:$J,"ACTIVO") -> 0
B15: K15 | C15: SALUD ORAL EN LOS TERRITORIOS | D15: =COUNTIFS('C COSTOS ESTADO FINANCIERO'!$D:$D,B15,'C COSTOS ESTADO FINANCIERO'!$J:$J,"ACTIVO") -> 0
... B49: U05 | C49: COORDINACION EN SALUD | D49: =COUNTIFS('C COSTOS ESTADO FINANCIERO'!$D:$D,B49,'C COSTOS ESTADO FINANCIERO'!$J:$J,"ACTIVO") -> 2

Sheet CENTROS DE COSTOS RESOLUCION
B1: CENTROS DE COSTOS RESOLUCION
B3: CÓDIGO CECO | C3: NOMBRE CENTROS DE COSTOS | D3: N° CECO E.F. ACTIVOS ASIGNADOS | E3: ¿EN LISTA UTILIZADOS?
B4: A01 | C4: AUDIOLOGIA Y AUDIOMETRÍA | D4: =COUNTIFS('C COSTOS ESTADO FINANCIERO'!$D:$D,B4,'C COSTOS ESTADO FINANCIERO'!$J:$J,"ACTIVO") -> 0 | E4: =IF(COUNTIF('CENTROS DE COSTOS UTILIZADOS'!$B:$B,B4)>0,"SÍ","NO") -> NO
B5: A02 | C5: CARDIOLOGÍA | D5: =COUNTIFS('C COSTOS ESTADO FINANCIERO'!$D:$D,B5,'C COSTOS ESTADO FINANCIERO'!$J:$J,"ACTIVO") -> 0 | E5: =IF(COUNTIF('CENTROS DE COSTOS UTILIZADOS'!$B:$B,B5)>0,"SÍ","NO") -> NO
B6: A03 | C6: DERMATOLOGÍA | D6: =COUNTIFS('C COSTOS ESTADO FINANCIERO'!$D:$D,B6,'C COSTOS ESTADO FINANCIERO'!$J:$J,"ACTIVO") -> 0 | E6: =IF(COUNTIF('CENTROS DE COSTOS UTILIZADOS'!$B:$B,B6)>0,"SÍ","NO") -> NO
B7: A04 | C7: ENDOCRINOLOGÍA | D7: =COUNTIFS('C COSTOS ESTADO FINANCIERO'!$D:$D,B7,'C COSTOS ESTADO FINANCIERO'!$J:$J,"ACTIVO") -> 0 | E7: =IF(COUNTIF('CENTROS DE COSTOS UTILIZADOS'!$B:$B,B7)>0,"SÍ","NO") -> NO
B8: A05 | C8: GERIATRÍA | D8: =COUNTIFS('C COSTOS ESTADO FINANCIERO'!$D:$D,B8,'C COSTOS ESTADO FINANCIERO'!$J:$J,"ACTIVO") -> 0 | E8: =IF(COUNTIF('CENTROS DE COSTOS UTILIZADOS'!$B:$B,B8)>0,"SÍ","NO") -> NO
B9: A06 | C9: GASTROENTEROLOGÍA | D9: =COUNTIFS('C COSTOS ESTADO FINANCIERO'!$D:$D,B9,'C COSTOS ESTADO FINANCIERO'!$J:$J,"ACTIVO") -> 0 | E9: =IF(COUNTIF('CENTROS DE COSTOS UTILIZADOS'!$B:$B,B9)>0,"SÍ","NO") -> NO
B10: A07 | C10: GENÉTICA | D10: =COUNTIFS('C COSTOS ESTADO FINANCIERO'!$D:$D,B10,'C COSTOS ESTADO FINANCIERO'!$J:$J,"ACTIVO") -> 0 | E10: =IF(COUNTIF('CENTROS DE COSTOS UTILIZADOS'!$B:$B,B10)>0,"SÍ","NO") -> NO
B11: A08 | C11: INMUNOHEMATOLOGÍA | D11: =COUNTIFS('C COSTOS ESTADO FINANCIERO'!$D:$D,B11,'C COSTOS ESTADO FINANCIERO'!$J:$J,"ACTIVO") -> 0 | E11: =IF(COUNTIF('CENTROS DE COSTOS UTILIZADOS'!$B:$B,B11)>0,"SÍ","NO") -> NO
B12: A09 | C12: NEFROLOGÍA | D12: =COUNTIFS('C COSTOS ESTADO FINANCIERO'!$D:$D,B12,'C COSTOS ESTADO FINANCIERO'!$J:$J,"ACTIVO") -> 0 | E12: =IF(COUNTIF('CENTROS DE COSTOS UTILIZADOS'!$B:$B,B12)>0,"SÍ","NO") -> NO
B13: A10 | C13: MEDICINA GENERAL | D13: =COUNTIFS('C COSTOS ESTADO FINANCIERO'!$D:$D,B13,'C COSTOS ESTADO FINANCIERO'!$J:$J,"ACTIVO") -> 8 | E13: =IF(COUNTIF('CENTROS DE COSTOS UTILIZADOS'!$B:$B,B13)>0,"SÍ","NO") -> SÍ
B14: A11 | C14: MEDICINA INTERNA | D14: =COUNTIFS('C COSTOS ESTADO FINANCIERO'!$D:$D,B14,'C COSTOS ESTADO FINANCIERO'!$J:$J,"ACTIVO") -> 0 | E14: =IF(COUNTIF('CENTROS DE COSTOS UTILIZADOS'!$B:$B,B14)>0,"SÍ","NO") -> NO
B15: A12 | C15: NEUMOLOGÍA | D15: =COUNTIFS('C COSTOS ESTADO FINANCIERO'!$D:$D,B15,'C COSTOS ESTADO FINANCIERO'!$J:$J,"ACTIVO") -> 0 | E15: =IF(COUNTIF('CENTROS DE COSTOS UTILIZADOS'!$B:$B,B15)>0,"SÍ","NO") -> NO
... B187: U05 | C187: COORDINACION EN SALUD | D187: =COUNTIFS('C COSTOS ESTADO FINANCIERO'!$D:$D,B187,'C COSTOS ESTADO FINANCIERO'!$J:$J,"ACTIVO") -> 2 | E187: =IF(COUNTIF('CENTROS DE COSTOS UTILIZADOS'!$B:$B,B187)>0,"SÍ","NO") -> SÍ

Sheet TABLA HERRAMIENTA
A1: COD_CECO_EF | B1: NOMBRE_CECO_EF | C1: COD_CECO_RES | D1: NOMBRE_CECO_RES | E1: SEDE | F1: TIPO_CECO | G1: ESTADO
A2: ='C COSTOS ESTADO FINANCIERO'!A2 -> 1020101 | B2: ='C COSTOS ESTADO FINANCIERO'!B2 -> HSLA-ARAUQUITA-CONSULTA Y PROCEDIMIENTOS | C2: ='C COSTOS ESTADO FINANCIERO'!D2 -> B01 | D2: ='C COSTOS ESTADO FINANCIERO'!E2 -> CONSULTA URGENCIAS | E2: ='C COSTOS ESTADO FINANCIERO'!I2 -> HSLA - Arauquita | F2: ='C COSTOS ESTADO FINANCIERO'!H2 -> PRODUCTIVO (final) | G2: ='C COSTOS ESTADO FINANCIERO'!J2 -> ACTIVO
A3: ='C COSTOS ESTADO FINANCIERO'!A3 -> 1020102 | B3: ='C COSTOS ESTADO FINANCIERO'!B3 -> HSLA-ARAUQUITA-OBSERVACIONES | C3: ='C COSTOS ESTADO FINANCIERO'!D3 -> B02 | D3: ='C COSTOS ESTADO FINANCIERO'!E3 -> OBSERVACIÓN | E3: ='C COSTOS ESTADO FINANCIERO'!I3 -> HSLA - Arauquita | F3: ='C COSTOS ESTADO FINANCIERO'!H3 -> PRODUCTIVO (final) | G3: ='C COSTOS ESTADO FINANCIERO'!J3 -> ACTIVO
A4: ='C COSTOS ESTADO FINANCIERO'!A4 -> 1020201 | B4: ='C COSTOS ESTADO FINANCIERO'!B4 -> HSLA-ARAUQUITA-CONSULTA EXTERNA | C4: ='C COSTOS ESTADO FINANCIERO'!D4 -> A10 | D4: ='C COSTOS ESTADO FINANCIERO'!E4 -> MEDICINA GENERAL | E4: ='C COSTOS ESTADO FINANCIERO'!I4 -> HSLA - Arauquita | F4: ='C COSTOS ESTADO FINANCIERO'!H4 -> PRODUCTIVO (final) | G4: ='C COSTOS ESTADO FINANCIERO'!J4 -> ACTIVO
A5: ='C COSTOS ESTADO FINANCIERO'!A5 -> 1020202 | B5: ='C COSTOS ESTADO FINANCIERO'!B5 -> HSLA-ARAUQUITA-CONSULTA ESPECIALIZADA | C5: ='C COSTOS ESTADO FINANCIERO'!D5 -> A32 | D5: ='C COSTOS ESTADO FINANCIERO'!E5 -> OTRAS CONSULTAS Y PROCEDIMIENTOS | E5: ='C COSTOS ESTADO FINANCIERO'!I5 -> HSLA - Arauquita | F5: ='C COSTOS ESTADO FINANCIERO'!H5 -> PRODUCTIVO (final) | G5: ='C COSTOS ESTADO FINANCIERO'!J5 -> ACTIVO
A6: ='C COSTOS ESTADO FINANCIERO'!A6 -> 1020203 | B6: ='C COSTOS ESTADO FINANCIERO'!B6 -> HSLA-ARAUQUITA-SALUD ORAL | C6: ='C COSTOS ESTADO FINANCIERO'!D6 -> E01 | D6: ='C COSTOS ESTADO FINANCIERO'!E6 -> ODONTOLOGÍA GENERAL | E6: ='C COSTOS ESTADO FINANCIERO'!I6 -> HSLA - Arauquita | F6: ='C COSTOS ESTADO FINANCIERO'!H6 -> PRODUCTIVO (final) | G6: ='C COSTOS ESTADO FINANCIERO'!J6 -> ACTIVO
A7: ='C COSTOS ESTADO FINANCIERO'!A7 -> 1020204 | B7: ='C COSTOS ESTADO FINANCIERO'!B7 -> HSLA-ARAUQUITA-PROMOCION Y MANTENIMIENTO | C7: ='C COSTOS ESTADO FINANCIERO'!D7 -> N03 | D7: ='C COSTOS ESTADO FINANCIERO'!E7 -> PROMOCIÓN Y PREVENCIÓN | E7: ='C COSTOS ESTADO FINANCIERO'!I7 -> HSLA - Arauquita | F7: ='C COSTOS ESTADO FINANCIERO'!H7 -> PRODUCTIVO (final) | G7: ='C COSTOS ESTADO FINANCIERO'!J7 -> ACTIVO
A8: ='C COSTOS ESTADO FINANCIERO'!A8 -> 1020205 | B8: ='C COSTOS ESTADO FINANCIERO'!B8 -> HSLA-ARAUQUITA-OTRAS ACTIVIDADES EXTRAMURALES | C8: ='C COSTOS ESTADO FINANCIERO'!D8 -> K25 | D8: ='C COSTOS ESTADO FINANCIERO'!E8 -> SALUD PUBLICA | E8: ='C COSTOS ESTADO FINANCIERO'!I8 -> HSLA - Arauquita | F8: ='C COSTOS ESTADO FINANCIERO'!H8 -> PRODUCTIVO (final) | G8: ='C COSTOS ESTADO FINANCIERO'!J8 -> ACTIVO
A9: ='C COSTOS ESTADO FINANCIERO'!A9 -> 1020301 | B9: ='C COSTOS ESTADO FINANCIERO'!B9 -> HSLA-ARAUQUITA-HOSPITALACION-ESTANCIA GENERAL | C9: ='C COSTOS ESTADO FINANCIERO'!D9 -> I01 | D9: ='C COSTOS ESTADO FINANCIERO'!E9 -> HOSPITALIZACIÓN GENERAL | E9: ='C COSTOS ESTADO FINANCIERO'!I9 -> HSLA - Arauquita | F9: ='C COSTOS ESTADO FINANCIERO'!H9 -> PRODUCTIVO (final) | G9: ='C COSTOS ESTADO FINANCIERO'!J9 -> ACTIVO
A10: ='C COSTOS ESTADO FINANCIERO'!A10 -> 1020302 | B10: ='C COSTOS ESTADO FINANCIERO'!B10 -> HSLA-ARAUQUITA-CUIDADOS INTENSIVOS | C10: ='C COSTOS ESTADO FINANCIERO'!D10 -> J02 | D10: ='C COSTOS ESTADO FINANCIERO'!E10 -> UCI ADULTOS | E10: ='C COSTOS ESTADO FINANCIERO'!I10 -> HSLA - Arauquita | F10: ='C COSTOS ESTADO FINANCIERO'!H10 -> PRODUCTIVO (final) | G10: ='C COSTOS ESTADO FINANCIERO'!J10 -> NO APLICA
A11: ='C COSTOS ESTADO FINANCIERO'!A11 -> 1020303 | B11: ='C COSTOS ESTADO FINANCIERO'!B11 -> HSLA-ARAUQUITA-CUIDADOS INTERMEDIOS | C11: ='C COSTOS ESTADO FINANCIERO'!D11 -> J05 | D11: ='C COSTOS ESTADO FINANCIERO'!E11 -> UCI INTERMEDIOS ADULTOS | E11: ='C COSTOS ESTADO FINANCIERO'!I11 -> HSLA - Arauquita | F11: ='C COSTOS ESTADO FINANCIERO'!H11 -> PRODUCTIVO (final) | G11: ='C COSTOS ESTADO FINANCIERO'!J11 -> NO APLICA
A12: ='C COSTOS ESTADO FINANCIERO'!A12 -> 1020304 | B12: ='C COSTOS ESTADO FINANCIERO'!B12 -> HSLA-ARAUQUITA-RECIEN NACIDOS | C12: ='C COSTOS ESTADO FINANCIERO'!D12 -> J09 | D12: ='C COSTOS ESTADO FINANCIERO'!E12 -> UNIDAD DE RECIÉN NACIDOS | E12: ='C COSTOS ESTADO FINANCIERO'!I12 -> HSLA - Arauquita | F12: ='C COSTOS ESTADO FINANCIERO'!H12 -> PRODUCTIVO (final) | G12: ='C COSTOS ESTADO FINANCIERO'!J12 -> VERIFICAR
A13: ='C COSTOS ESTADO FINANCIERO'!A13 -> 1020305 | B13: ='C COSTOS ESTADO FINANCIERO'!B13 -> HSLA-ARAUQUITA-HOSPITALIZACI.N SALUD MENTAL | C13: ='C COSTOS ESTADO FINANCIERO'!D13 -> J10 | D13: ='C COSTOS ESTADO FINANCIERO'!E13 -> UNIDAD SALUD MENTAL Y DESINTOXICACIÓN (BAJA COMPLEJIDAD) | E13: ='C COSTOS ESTADO FINANCIERO'!I13 -> HSLA - Arauquita | F13: ='C COSTOS ESTADO FINANCIERO'!H13 -> PRODUCTIVO (final) | G13: ='C COSTOS ESTADO FINANCIERO'!J13 -> NO APLICA
... A550: ='C COSTOS ESTADO FINANCIERO'!A550 -> 4142217 | B550: ='C COSTOS ESTADO FINANCIERO'!B550 -> ESE01 - TAME - SISTEMA ELECTRICO | C550: ='C COSTOS ESTADO FINANCIERO'!D550 -> R03 | D550: ='C COSTOS ESTADO FINANCIERO'!E550 -> MANTENIMIENTO | E550: ='C COSTOS ESTADO FINANCIERO'!I550 -> ESE01 - Sede Administrativa (Tame) | F550: ='C COSTOS ESTADO FINANCIERO'!H550 -> ADMINISTRATIVO | G550: ='C COSTOS ESTADO FINANCIERO'!J550 -> ACTIVO
